house_info/__init__.py
house_info/base.py
house_info/mixins.py
house_info/my_home.py
house_info/sh.py
house_info/station_area.py
house_info/utils.py
house_info-0.0.4.dist-info/LICENSE
house_info-0.0.4.dist-info/METADATA
house_info-0.0.4.dist-info/WHEEL
house_info-0.0.4.dist-info/top_level.txt
house_info-0.0.4.dist-info/RECORD
