Metadata-Version: 2.1
Name: house-info
Version: 0.0.4
Summary: 공공 주택 공고 정보 수집
Home-page: https://github.com/c2-house/house-info
Author: Jungminchae
Author-email: minggae0629@gmail.com
License: UNKNOWN
Keywords: house-info
Platform: UNKNOWN
Classifier: Programming Language :: Python :: 3
Classifier: License :: OSI Approved :: MIT License
Classifier: Operating System :: OS Independent
Requires-Python: >=3
License-File: LICENSE
Requires-Dist: selenium
Requires-Dist: requests
Requires-Dist: beautifulsoup4
Requires-Dist: pandas
